Workbook

Sheet DRE 2026
A1: Aurora S.A. — Demonstração do Resultado do Exercício
A2: Relatório Financeiro Consolidado | Exercício de 2026 (Valores em R$)
A4: Conta DRE | B4: Valor (R$) | C4: % da Receita Bruta
A5: Receita Bruta | B5: 52800000 | C5: =B5/$B$5 -> 1
A6: Deduções da Receita (Impostos sobre Operações / Estornos) | B6: -4750000 | C6: =B6/$B$5 -> -0.089962121
A7: Receita Líquida | B7: =B5+B6 -> 48050000 | C7: =B7/$B$5 -> 0.91003788
A8: Custos Operacionais (Captação / Infraestrutura / TI) | B8: -18920000 | C8: =B8/$B$5 -> -0.35833333
A9: Lucro Bruto | B9: =B7+B8 -> 29130000 | C9: =B9/$B$5 -> 0.55170455
A10: Despesas Administrativas | B10: -5680000 | C10: =B10/$B$5 -> -0.10757576
A11: Despesas Comerciais & Marketing | B11: -5950000 | C11: =B11/$B$5 -> -0.11268939
A12: Despesas Financeiras Líquidas | B12: -1120000 | C12: =B12/$B$5 -> -0.021212121
A13: Resultado Operacional (EBIT) | B13: =B9+SUM(B10:B12) -> 16380000 | C13: =B13/$B$5 -> 0.31022727
A14: Impostos (IRPJ e CSLL) | B14: -3050000 | C14: =B14/$B$5 -> -0.057765152
A15: Lucro Líquido do Exercício | B15: =B13+B14 -> 13330000 | C15: =B15/$B$5 -> 0.25246212

Sheet Comparativo Mensal
A1: Aurora S.A. — Evolução Mensal do Resultado (2026)
A2: Detalhamento Mensal de Receita, Custos, Despesas e Lucros (em R$)
A4: Mês | B4: Receita Líquida | C4: Custos Operacionais | D4: Despesas Operacionais | E4: Lucro Operacional | F4: Lucro Líquido
A5: Janeiro | B5: 3800000 | C5: 1500000 | D5: 1050000 | E5: =B5-C5-D5 -> 1250000 | F5: =E5*0.8 -> 1000000
A6: Fevereiro | B6: 3860000 | C6: 1520000 | D6: 1060000 | E6: =B6-C6-D6 -> 1280000 | F6: =E6*0.8 -> 1024000
A7: Março | B7: 4020000 | C7: 1580000 | D7: 1080000 | E7: =B7-C7-D7 -> 1360000 | F7: =E7*0.8 -> 1088000
A8: Abril | B8: 3950000 | C8: 1550000 | D8: 1070000 | E8: =B8-C8-D8 -> 1330000 | F8: =E8*0.8 -> 1064000
A9: Maio | B9: 4100000 | C9: 1610000 | D9: 1090000 | E9: =B9-C9-D9 -> 1400000 | F9: =E9*0.8 -> 1120000
A10: Junho | B10: 4180000 | C10: 1640000 | D10: 1100000 | E10: =B10-C10-D10 -> 1440000 | F10: =E10*0.8 -> 1152000
A11: Julho | B11: 4250000 | C11: 1670000 | D11: 1110000 | E11: =B11-C11-D11 -> 1470000 | F11: =E11*0.8 -> 1176000
A12: Agosto | B12: 4200000 | C12: 1650000 | D12: 1105000 | E12: =B12-C12-D12 -> 1445000 | F12: =E12*0.8 -> 1156000
A13: Setembro | B13: 4380000 | C13: 1720000 | D13: 1130000 | E13: =B13-C13-D13 -> 1530000 | F13: =E13*0.8 -> 1224000
A14: Outubro | B14: 4460000 | C14: 1750000 | D14: 1140000 | E14: =B14-C14-D14 -> 1570000 | F14: =E14*0.8 -> 1256000
A15: Novembro | B15: 4550000 | C15: 1790000 | D15: 1155000 | E15: =B15-C15-D15 -> 1605000 | F15: =E15*0.8 -> 1284000
A16: Dezembro | B16: 4650000 | C16: 1830000 | D16: 1170000 | E16: =B16-C16-D16 -> 1650000 | F16: =E16*0.8 -> 1320000
A17: Total Acumulado | B17: =SUM(B5:B16) -> 50400000 | C17: =SUM(C5:C16) -> 19810000 | D17: =SUM(D5:D16) -> 13260000 | E17: =SUM(E5:E16) -> 17330000 | F17: =SUM(F5:F16) -> 13864000

Sheet Indicadores Financeiros
A1: Aurora S.A. — Indicadores Financeiros & Métricas de Performance
A2: Visão Sintética de Margens, Eficiência e Métricas Corporativas (2026)
A4: Indicador | B4: Fórmula / Critério | C4: Valor / Percentual
A5: Receita Total (Líquida) | B5: Soma da Receita Líquida no Ano | C5: ='DRE 2026'!B7 -> 48050000
A6: Receita Média Mensal | B6: Média da Receita Líquida Mensal | C6: =AVERAGE('Comparativo Mensal'!B5:B16) -> 4200000
A7: Crescimento Anual | B7: Variação em relação ao exercício anterior (2025) | C7: 0.168
A8: Margem Bruta | B8: Lucro Bruto / Receita Líquida | C8: ='DRE 2026'!B9/'DRE 2026'!B7 -> 0.6062435
A9: Margem Operacional | B9: Resultado Operacional / Receita Líquida | C9: ='DRE 2026'!B13/'DRE 2026'!B7 -> 0.3408949
A10: Margem Líquida | B10: Lucro Líquido / Receita Líquida | C10: ='DRE 2026'!B15/'DRE 2026'!B7 -> 0.27741935
A11: EBITDA | B11: Resultado Operacional + Depreciação/Amortização | C11: ='DRE 2026'!B13+2100000 -> 18480000
A12: Ticket Médio por Cliente | B12: Receita Líquida / Base de Clientes Ativos (1.850) | C12: ='DRE 2026'!B7/1850 -> 25972.973
A13: Receita por Colaborador | B13: Receita Líquida / Colaboradores (420) | C13: ='DRE 2026'!B7/420 -> 114404.76
A14: Custo Operacional Médio Mensal | B14: Média dos Custos Operacionais Mensais | C14: =AVERAGE('Comparativo Mensal'!C5:C16) -> 1650833.3

Sheet Dashboard
A1: Aurora S.A. — Painel Executivo Financeiro
A2: Principais Métricas de Resultado e Indicadores Chave de Desempenho (2026)
A4: Receita Total (Líquida) | C4: Lucro Líquido | E4: Receita Média Mensal | G4: Crescimento do Ano
A5: ='DRE 2026'!B7 -> 48050000 | C5: ='DRE 2026'!B15 -> 13330000 | E5: ='Indicadores Financeiros'!C6 -> 4200000 | G5: ='Indicadores Financeiros'!C7 -> 0.168
A7: Melhor Mês (Faturamento) | C7: Pior Mês (Faturamento) | E7: Percentual de Custos | G7: Percentual de Despesas
A8: =INDEX('Comparativo Mensal'!A5:A16, MATCH(MAX('Comparativo Mensal'!B5:B16), 'Comparativo Mensal'!B5:B16, 0)) -> Dezembro | C8: =INDEX('Comparativo Mensal'!A5:A16, MATCH(MIN('Comparativo Mensal'!B5:B16), 'Comparativo Mensal'!B5:B16, 0)) -> Janeiro | E8: =-'DRE 2026'!B8/'DRE 2026'!B7 -> 0.3937565 | G8: =-SUM('DRE 2026'!B10:B12)/'DRE 2026'!B7 -> 0.2653486
A10: Resumo das Principais Contas DRE
A11: Conta DRE | B11: Valor Consolidado (R$) | C11: % S/ Receita Líquida
A12: Receita Bruta | B12: ='DRE 2026'!B5 -> 52800000 | C12: =B12/$B$13 -> 1.0988554
A13: Receita Líquida | B13: ='DRE 2026'!B7 -> 48050000 | C13: =B13/$B$13 -> 1
A14: Lucro Bruto | B14: ='DRE 2026'!B9 -> 29130000 | C14: =B14/$B$13 -> 0.6062435
A15: Resultado Operacional (EBIT) | B15: ='DRE 2026'!B13 -> 16380000 | C15: =B15/$B$13 -> 0.3408949
A16: EBITDA | B16: ='Indicadores Financeiros'!C11 -> 18480000 | C16: =B16/$B$13 -> 0.38459938
A17: Lucro Líquido | B17: ='DRE 2026'!B15 -> 13330000 | C17: =B17/$B$13 -> 0.27741935
